ltermio/__init__.py
ltermio/color256.py
ltermio/cursor.py
ltermio/termkey.py
ltermio/termouse.py
ltermio/unicon.py
ltermio-0.6.3.dist-info/METADATA
ltermio-0.6.3.dist-info/WHEEL
ltermio-0.6.3.dist-info/entry_points.txt
ltermio-0.6.3.dist-info/licenses/LICENSE
ltermio-0.6.3.dist-info/RECORD
