Metadata-Version: 2.1
Name: ltermio
Version: 0.6.3
Summary: A lightweight POSIX terminal I/O library
Project-URL: Homepage, https://github.com/brookssu/ltermio
Author-email: Brooks Su <yipeng00@gmail.com>
License:                                  Apache License
License-File: LICENSE
Keywords: ansi,color,color256,colour,composing,csi,curses,cursor,getch,keyboard,ltermio,mouse,posix,terminal,termios,termkey,termouse,xfree86,xterm
Classifier: Development Status :: 4 - Beta
Classifier: Environment :: Console
Classifier: Intended Audience :: Developers
Classifier: License :: OSI Approved :: Apache Software License
Classifier: Natural Language :: English
Classifier: Operating System :: MacOS :: MacOS X
Classifier: Operating System :: POSIX
Classifier: Operating System :: Unix
Classifier: Programming Language :: Python :: 3.9
Classifier: Programming Language :: Python :: 3.10
Classifier: Programming Language :: Python :: 3.11
Classifier: Topic :: Software Development :: Libraries :: Python Modules
Requires-Python: >=3.7
